tosspayments/__init__.py
tosspayments/main.py
python_tosspayments-1.1.0.dist-info/LICENSE.txt
python_tosspayments-1.1.0.dist-info/METADATA
python_tosspayments-1.1.0.dist-info/WHEEL
python_tosspayments-1.1.0.dist-info/top_level.txt
python_tosspayments-1.1.0.dist-info/RECORD
