Metadata-Version: 2.1
Name: python-tosspayments
Version: 1.1.0
Summary: Toss Payments SDK for python. 토스페이먼츠가 아닌 제 3자가 만든 SDK입니다.
Home-page: https://github.com/GisangLee/python-tosspayment
Author: jsonlee
Author-email: dudegs.py@gmail.com
License: MIT
Keywords: toss,toss payment,payment
Classifier: Programming Language :: Python :: 3
Classifier: License :: OSI Approved :: MIT License
Requires-Python: >=3.8
License-File: LICENSE.txt
Requires-Dist: requests
